{"changelog.md":"B2Gi2Fdt","computer_assembly.md":"BeVGlYo-","computer_cpu.md":"CZTQbvl4","computer_cpu_control-components.md":"DfHray9l","computer_cpu_control-memory-deploy.md":"BD4RGRW6","computer_cpu_control-memory.md":"B8ddBZnc","computer_cpu_decoder-visibility.md":"Bdh1hskj","computer_cpu_sequencer.md":"BCauchH2","computer_instructions_add.md":"sguh1KsG","computer_instructions_and.md":"BHGwRVLV","computer_instructions_call.md":"BtvgrL_-","computer_instructions_cli.md":"BwBC37st","computer_instructions_cmp.md":"5tRNlLQi","computer_instructions_dec.md":"DdZadtNM","computer_instructions_hlt.md":"CBnNFAN9","computer_instructions_in.md":"C6UMdK7u","computer_instructions_inc.md":"BpojGyNy","computer_instructions_index.md":"-uUh2Mmu","computer_instructions_int.md":"Dfns40l2","computer_instructions_iret.md":"B9dZkX9S","computer_instructions_jc.md":"DXEN-AJY","computer_instructions_jmp.md":"BaIvjway","computer_instructions_jnc.md":"CXOKfH6o","computer_instructions_jno.md":"DcGFtOF7","computer_instructions_jns.md":"BZBgbdQU","computer_instructions_jnz.md":"TYXBGmeQ","computer_instructions_jo.md":"BwaHCwI3","computer_instructions_js.md":"Cm7odHVZ","computer_instructions_jz.md":"BEYvP9Ur","computer_instructions_mov.md":"BTqvWpOd","computer_instructions_neg.md":"BKWlv5e5","computer_instructions_not.md":"CH9wfJhO","computer_instructions_or.md":"DyxRY7Da","computer_instructions_out.md":"DijQIdZi","computer_instructions_pop.md":"Clbh3yTn","computer_instructions_push.md":"PFJasyrP","computer_instructions_ret.md":"IeItwsm0","computer_instructions_sti.md":"OJGP4Ght","computer_instructions_sub.md":"BWP9-QIG","computer_instructions_xor.md":"B426R_jn","computer_memory.md":"8JVy3wZP","encoding_encoding.md":"D3pW9v0Z","encoding_index.md":"CQ9aC0lH","index.md":"KkGLcF_2","instructioncycle_index.md":"5D_o7Kal","instructioncycle_instructioncycle.md":"B6x_xMCA","io_devices_clock.md":"BD8Jv5Vz","io_devices_f10.md":"BYLxQ6Vg","io_devices_index.md":"CJD8jldH","io_devices_keyboard.md":"BHCzTiv5","io_devices_printer.md":"BsoWvXH3","io_devices_screen.md":"CMWBMZS8","io_devices_switches-and-leds.md":"Bze-wle0","io_index.md":"9YMTfsbz","io_modules_handshake.md":"D_TH1d7o","io_modules_index.md":"B2A288-n","io_modules_pic.md":"AchqvC8y","io_modules_pio.md":"D_j-X4ra","io_modules_timer.md":"BQ6T7KO1","reference_ascii.md":"DBBybGUN"}
