{"changelog.md":"DnBkIqKw","computer_assembly.md":"D7BjD9fu","computer_cpu.md":"CUZzZQ4U","computer_cpu_control-components.md":"xkRxJFVG","computer_cpu_control-memory-deploy.md":"DXnyU5Sh","computer_cpu_control-memory.md":"BvBZpEHc","computer_cpu_decoder-visibility.md":"Fdsbq_ni","computer_cpu_sequencer.md":"DxVKY7GH","computer_instructions_adc.md":"CGNWctAj","computer_instructions_add.md":"C3_Z9kzg","computer_instructions_and.md":"BPExgfYD","computer_instructions_call.md":"CAZufuBv","computer_instructions_cli.md":"C8U1IE4x","computer_instructions_cmp.md":"CyUm_mfS","computer_instructions_dec.md":"CeX6S2qj","computer_instructions_hlt.md":"D3R3mZNx","computer_instructions_in.md":"GD5SHTBc","computer_instructions_inc.md":"H6UQIAYz","computer_instructions_index.md":"DJXcC8Ku","computer_instructions_int.md":"B1qwS6UT","computer_instructions_iret.md":"BjRxQYeR","computer_instructions_jc.md":"BAPxXwAy","computer_instructions_jmp.md":"CVDcy4XW","computer_instructions_jnc.md":"D-yBM6eH","computer_instructions_jno.md":"DgGfthdw","computer_instructions_jns.md":"FkigHaSd","computer_instructions_jnz.md":"CFW7FYms","computer_instructions_jo.md":"cWNBEOT9","computer_instructions_js.md":"Cj0_Y5B2","computer_instructions_jz.md":"6hNQrgit","computer_instructions_mov.md":"LY4z1z2e","computer_instructions_neg.md":"Cvg_J3e2","computer_instructions_nop.md":"Cz0YBh19","computer_instructions_not.md":"jgIsy9kw","computer_instructions_or.md":"MoS0nu1-","computer_instructions_out.md":"iWWJQJcN","computer_instructions_pop.md":"D4I_HY7c","computer_instructions_popf.md":"D7O-q3Qr","computer_instructions_push.md":"DyFF1f9l","computer_instructions_pushf.md":"DrlRYI-w","computer_instructions_ret.md":"qUDRUOCJ","computer_instructions_sbb.md":"B5wxX9Dp","computer_instructions_sti.md":"DzgDJWl2","computer_instructions_sub.md":"Dn7OXH7w","computer_instructions_test.md":"R888OLvk","computer_instructions_xor.md":"B2dMYnDT","computer_memory.md":"Bi5X0ETO","index.md":"Bf79atPX","io_devices_clock.md":"DEgrq9m2","io_devices_f10.md":"qTE4QpMz","io_devices_index.md":"gqMF7vy4","io_devices_keyboard.md":"Dm4UunN-","io_devices_printer.md":"DKxpD58_","io_devices_screen.md":"BJg3-LXF","io_devices_switches-and-leds.md":"DMu6lLBy","io_index.md":"Di_oaWz5","io_modules_handshake.md":"uqAvwXJO","io_modules_index.md":"BsU5-Lx-","io_modules_pic.md":"CCCMk7iJ","io_modules_pio.md":"s4-tqUsB","io_modules_timer.md":"BdWilJdl","reference_ascii.md":"iRC_eL3J","reference_encoding.md":"DBj197Oq","reference_instructioncycle.md":"qrdbczTD"}
