{"changelog.md":"LnOiMt_z","computer_assembly.md":"B37Pzeog","computer_cpu.md":"CdZxGZ0R","computer_cpu_control-components.md":"mmhBdXBY","computer_cpu_control-memory-deploy.md":"DYVTnlng","computer_cpu_control-memory.md":"BJg0Utfa","computer_cpu_decoder-visibility.md":"lOBE7WTL","computer_cpu_sequencer.md":"C6554dXs","computer_instructions_adc.md":"xXETMV7M","computer_instructions_add.md":"DKWqZG_c","computer_instructions_and.md":"DDdXnqm2","computer_instructions_call.md":"U-Kbqdm-","computer_instructions_cli.md":"DiTkxTR8","computer_instructions_cmp.md":"D-YAtpac","computer_instructions_dec.md":"BCFT9Mgt","computer_instructions_hlt.md":"CF629_Sq","computer_instructions_in.md":"CdTnSY5M","computer_instructions_inc.md":"D0NQ8bst","computer_instructions_index.md":"DaDKSIck","computer_instructions_int.md":"DUbg5dKH","computer_instructions_iret.md":"C0ei6wG1","computer_instructions_jc.md":"DXrWMqD_","computer_instructions_jmp.md":"CbHsuxTg","computer_instructions_jnc.md":"D37qGE8y","computer_instructions_jno.md":"BGDIY_Js","computer_instructions_jns.md":"1p9plUns","computer_instructions_jnz.md":"D6jSNwcA","computer_instructions_jo.md":"DfQm1pVj","computer_instructions_js.md":"DCmGH5LW","computer_instructions_jz.md":"nXRwoKVa","computer_instructions_mov.md":"Cpkxe7SK","computer_instructions_neg.md":"B3j3U2zA","computer_instructions_nop.md":"B_SYeqIB","computer_instructions_not.md":"BNpbZq1w","computer_instructions_or.md":"Cbn9gnHu","computer_instructions_out.md":"BvZLgkwd","computer_instructions_pop.md":"B2PDODIo","computer_instructions_popf.md":"Fck9UVSg","computer_instructions_push.md":"C4oJIohk","computer_instructions_pushf.md":"BmUtpQP9","computer_instructions_ret.md":"9jyBfI_I","computer_instructions_sbb.md":"43iOcZeN","computer_instructions_sti.md":"DEt-NMtd","computer_instructions_sub.md":"CRbBZWSe","computer_instructions_test.md":"qsWrztx5","computer_instructions_xor.md":"BFDG9_Ol","computer_memory.md":"BfBBHX1G","index.md":"CppYSVzv","io_devices_clock.md":"vvq1qR5p","io_devices_f10.md":"XKkYWJk5","io_devices_index.md":"DjEQ5h7O","io_devices_keyboard.md":"BVElRswL","io_devices_printer.md":"DuigYLSo","io_devices_screen.md":"CNYAs5IN","io_devices_switches-and-leds.md":"CUWHKfka","io_index.md":"ClxJdNCg","io_modules_handshake.md":"CLKohfCT","io_modules_index.md":"mpfh4HK4","io_modules_pic.md":"gKU0rLwA","io_modules_pio.md":"Dbrjyuge","io_modules_timer.md":"CHZV_QDU","reference_ascii.md":"8u6UPGGO","reference_encoding.md":"CE8KHrNK","reference_instructioncycle.md":"pb22QeIH"}
